discord/ext/boardgames/__init__.py
discord/ext/boardgames/boardgames.py
discord/ext/boardgames/converter.py
discord_ext_boardgames-0.2.3.dist-info/LICENSE
discord_ext_boardgames-0.2.3.dist-info/METADATA
discord_ext_boardgames-0.2.3.dist-info/WHEEL
discord_ext_boardgames-0.2.3.dist-info/top_level.txt
discord_ext_boardgames-0.2.3.dist-info/RECORD
