Metadata-Version: 2.1
Name: discord-ext-boardgames
Version: 0.2.3
Summary: Interactive board game session for discord.py
Home-page: https://github.com/bijij/discord-ext-boardgames
Author: bijij
License: MIT
Platform: UNKNOWN
Requires-Dist: discord.py (>=1.0)
